d20/__init__.py
d20/version.py
d20/Actions/__init__.py
d20/Actions/TestAction/__init__.py
d20/BackStories/__init__.py
d20/Manual/BattleMap.py
d20/Manual/Config.py
d20/Manual/Console.py
d20/Manual/Entry.py
d20/Manual/Exceptions.py
d20/Manual/GameMaster.py
d20/Manual/Logger.py
d20/Manual/Options.py
d20/Manual/RPC.py
d20/Manual/Registration.py
d20/Manual/Shell.py
d20/Manual/Templates.py
d20/Manual/Temporary.py
d20/Manual/Trackers.py
d20/Manual/Utils.py
d20/Manual/__init__.py
d20/Manual/Facts/Facts.py
d20/Manual/Facts/Fields.py
d20/Manual/Facts/__init__.py
d20/NPCS/HashNPC.py
d20/NPCS/MimeTypeNPC.py
d20/NPCS/__init__.py
d20/Players/__init__.py
d20/Screens/JsonScreen.py
d20/Screens/YamlScreen.py
d20/Screens/__init__.py
d20_framework-0.5.0.dist-info/LICENSE
d20_framework-0.5.0.dist-info/METADATA
d20_framework-0.5.0.dist-info/WHEEL
d20_framework-0.5.0.dist-info/entry_points.txt
d20_framework-0.5.0.dist-info/top_level.txt
d20_framework-0.5.0.dist-info/RECORD
