Metadata-Version: 2.1
Name: d20-framework
Version: 0.5.0
Summary: Automated Static Analysis Framework
Home-page: https://github.com/MITRECND/d20
Author: MITRE
Author-email: 
License: UNKNOWN
Platform: UNKNOWN
Classifier: License :: OSI Approved :: Apache Software License
Classifier: Programming Language :: Python
Classifier: Programming Language :: Python :: 3.7
Classifier: Programming Language :: Python :: 3.8
Classifier: Programming Language :: Python :: 3.9
Classifier: Programming Language :: Python :: 3.10
Classifier: Topic :: Security
Requires-Python: >=3.7
License-File: LICENSE
Requires-Dist: python-magic
Requires-Dist: ssdeep
Requires-Dist: pyyaml (<5.2,>=5.1)
Requires-Dist: requests
Requires-Dist: packaging
Requires-Dist: cerberus
Requires-Dist: texttable
